{
    "enabled": true,
    "neededInstalledMods": [],
    "neededUninstalledMods": [],
    "spawns": [
        {
            "id": "clefairy-twilight-1",
            "pokemon": "clefairy",
            "presets": [
                "natural_twilight"
            ],
            "type": "pokemon",
            "context": "grounded",
            "bucket": "common",
            "level": "4-16",
            "weight": 30.0,
            "condition": {
                "biomes": [
                    "twilightforest:clearing"
                ]
            }
        }
    ]
}